{
  "project_info": {
    "project_number": "803118826002",
    "project_id": "technical-support-e8963",
    "storage_bucket": "technical-support-e8963.appspot.com"
  },
  "client": [
    {
      "client_info": {
        "mobilesdk_app_id": "1:803118826002:android:0942c688c88aff9abd8ecb",
        "android_client_info": {
          "package_name": "com.example.technicalsupport"
        }
      },
      "oauth_client": [
        {
          "client_id": "803118826002-u1atgb7aep7bt67r4mfb142niep70md6.apps.googleusercontent.com",
          "client_type": 3
        }
      ],
      "api_key": [
        {
          "current_key": "AIzaSyDiKfMFRwmCh-U663AFDrTF55kN07yUI2A"
        }
      ],
      "services": {
        "appinvite_service": {
          "other_platform_oauth_client": [
            {
              "client_id": "803118826002-u1atgb7aep7bt67r4mfb142niep70md6.apps.googleusercontent.com",
              "client_type": 3
            }
          ]
        }
      }
    }
  ],
  "configuration_version": "1"
}